zdoc/__init__.py
zdoc/main.py
zulip_doc-0.4.0.dist-info/METADATA
zulip_doc-0.4.0.dist-info/WHEEL
zulip_doc-0.4.0.dist-info/entry_points.txt
zulip_doc-0.4.0.dist-info/licenses/LICENSE
zulip_doc-0.4.0.dist-info/RECORD
