Metadata-Version: 2.1
Name: zulip-doc
Version: 0.4.0
Summary: Zulip service that checks user presence for Duty of Care responsibilities for remote teams
Home-page: https://github.com/pizzapanther/zulip-doc
Author-Email: Paul Bailey <paul@neutron.studio>
License: MIT
Project-URL: Homepage, https://github.com/pizzapanther/zulip-doc
Requires-Python: >=3.8
Requires-Dist: zulip>=0.8.2
Requires-Dist: typer>=0.9.0
Requires-Dist: humanize>=4.7.0
